operis/utils.py
operis/log.py
operis/__init__.py
operis/management/__init__.py
operis/management/commands/collect-static-ember.py
operis/management/commands/generate-ember.py
operis/management/commands/__init__.py
django_operis-0.5.dist-info/DESCRIPTION.rst
django_operis-0.5.dist-info/metadata.json
django_operis-0.5.dist-info/WHEEL
django_operis-0.5.dist-info/RECORD
django_operis-0.5.dist-info/METADATA
django_operis-0.5.dist-info/top_level.txt
