Metadata-Version: 2.0
Name: django-operis
Version: 0.5
Summary: Autogeneration of Ember Models from Django Models
Home-page: https://github.com/Goldcap/django-operis
Author: Andy Madsen
Author-email: amadsen@operislabs.com
License: MIT
Keywords: django-rest-framework ember django generator
Platform: UNKNOWN
Classifier: Development Status :: 3 - Alpha
Classifier: Intended Audience :: Developers
Classifier: Topic :: Software Development :: WWW/HTTP
Classifier: License :: OSI Approved :: MIT License
Classifier: Programming Language :: Python :: 2
Classifier: Programming Language :: Python :: 2.6
Classifier: Programming Language :: Python :: 2.7
Classifier: Programming Language :: Python :: 3
Classifier: Programming Language :: Python :: 3.2
Classifier: Programming Language :: Python :: 3.3
Classifier: Programming Language :: Python :: 3.4
Requires-Dist: django
Requires-Dist: djangorestframework
Requires-Dist: django-jinja
Provides-Extra: dev
Requires-Dist: check-manifest; extra == 'dev'
Provides-Extra: test
Requires-Dist: coverage; extra == 'test'
